{"data":{"site":{"siteMetadata":{"title":"Este es un Hotfix!","author":"Veronica Clavijo"}},"markdownRemark":{"id":"4656c2ea-1542-52ac-895c-7859493e75d7","excerpt":"Inicio","html":"<p>Inicio</p>","frontmatter":{"title":"Todo lo que sé de git submodules","date":"June 15, 2019","description":"Git submodules"}}},"pageContext":{"isCreatedByStatefulCreatePages":false,"slug":"/15-06-2019-all-i-know-about-submodules/","previous":{"fields":{"slug":"/03-06-2019-things-i-use/"},"frontmatter":{"title":"Las cosas que uso"}},"next":{"fields":{"slug":"/18-07-2019-dmesg-to-the-rescue/"},"frontmatter":{"title":"Wifi en Debian Buster y dmesg"}}}}